zowe/workflows_for_zowe_sdk/__init__.py
zowe/workflows_for_zowe_sdk/workflows.py
zowe/workflows_for_zowe_sdk/response/__init__.py
zowe/workflows_for_zowe_sdk/response/workflows.py
zowe_workflows_for_zowe_sdk-1.0.0.dev24.dist-info/METADATA
zowe_workflows_for_zowe_sdk-1.0.0.dev24.dist-info/WHEEL
zowe_workflows_for_zowe_sdk-1.0.0.dev24.dist-info/top_level.txt
zowe_workflows_for_zowe_sdk-1.0.0.dev24.dist-info/RECORD
