Metadata-Version: 2.4
Name: zowe_workflows_for_zowe_sdk
Version: 1.0.0.dev24
Summary: Zowe Python SDK - z/OSMF Workflows package
Home-page: https://github.com/zowe/zowe-client-python-sdk
Author: Zowe
Author-email: zowe.robot@gmail.com
License: EPL-2.0
Classifier: Programming Language :: Python :: 3
Classifier: Programming Language :: Python :: 3.10
Classifier: License :: OSI Approved :: Eclipse Public License 2.0 (EPL-2.0)
Requires-Dist: zowe.core_for_zowe_sdk~=1.0.0-dev24
Dynamic: author
Dynamic: author-email
Dynamic: classifier
Dynamic: description
Dynamic: description-content-type
Dynamic: home-page
Dynamic: license
Dynamic: requires-dist
Dynamic: summary
